django_force_reset_password/__init__.py
django_force_reset_password/admin.py
django_force_reset_password/middleware.py
django_force_reset_password/models.py
django_force_reset_password/tests.py
django_force_reset_password/views.py
django_force_reset_password/migrations/__init__.py
django_force_reset_password-0.1.dist-info/DESCRIPTION.rst
django_force_reset_password-0.1.dist-info/METADATA
django_force_reset_password-0.1.dist-info/RECORD
django_force_reset_password-0.1.dist-info/WHEEL
django_force_reset_password-0.1.dist-info/metadata.json
django_force_reset_password-0.1.dist-info/top_level.txt
