Metadata-Version: 2.0
Name: django-force-reset-password
Version: 0.1
Summary: A simple Django app to force reset passwords.
Home-page: https://github.com/abdullatheef/django_force_reset_password
Author: Abdul Latheef
Author-email: latheefvkpadi@gmail.com
License: MIT License
Platform: UNKNOWN
Classifier: Environment :: Web Environment
Classifier: Framework :: Django
Classifier: Framework :: Django :: 1.8
Classifier: Intended Audience :: Developers
Classifier: License :: OSI Approved :: MIT License
Classifier: Operating System :: OS Independent
Classifier: Programming Language :: Python
Classifier: Programming Language :: Python :: 2.7
Classifier: Topic :: Internet :: WWW/HTTP
Classifier: Topic :: Internet :: WWW/HTTP :: Dynamic Content
